distillable_vision_transformer/__init__.py
distillable_vision_transformer/model.py
distillable_vision_transformer/utils.py
distillable_vision_transformer-1.0.1.dist-info/LICENSE
distillable_vision_transformer-1.0.1.dist-info/METADATA
distillable_vision_transformer-1.0.1.dist-info/WHEEL
distillable_vision_transformer-1.0.1.dist-info/top_level.txt
distillable_vision_transformer-1.0.1.dist-info/RECORD
