Metadata-Version: 2.1
Name: distillable-vision-transformer
Version: 1.0.1
Summary: A PyTorch vision transformer for distillation.
Home-page: https://github.com/Graeme22/DistillableVisionTransformer
Author: Graeme Holliday
Author-email: gholliday2@hotmail.com
License: Apache
Platform: UNKNOWN
Classifier: License :: OSI Approved :: Apache Software License
Classifier: Programming Language :: Python
Classifier: Programming Language :: Python :: 3
Classifier: Programming Language :: Python :: 3.6
Requires-Python: >=3.5.0
Requires-Dist: torch (>=1.5.0)
Requires-Dist: numpy
